README.md
setup.py
cfdiclient/Auth.py
cfdiclient/__init__.py
cfdiclient/format_strings.py
cfdiclient/utils.py
kea_cfdiclient.egg-info/PKG-INFO
kea_cfdiclient.egg-info/SOURCES.txt
kea_cfdiclient.egg-info/dependency_links.txt
kea_cfdiclient.egg-info/not-zip-safe
kea_cfdiclient.egg-info/top_level.txt