Metadata-Version: 1.0
Name: kea-cfdiclient
Version: 0.4
Summary: Client for CFDI
Home-page: http://kea.mx/
Author: Daniel Hernandez
Author-email: dhernandez@kea.mx
License: MIT
Platform: UNKNOWN
